datawig/__init__.py
datawig/_hpo.py
datawig/calibration.py
datawig/column_encoders.py
datawig/evaluation.py
datawig/imputer.py
datawig/iterators.py
datawig/mxnet_input_symbols.py
datawig/simple_imputer.py
datawig/utils.py
test/__init__.py
test/conftest.py
test/test_calibration.py
test/test_column_encoders.py
test/test_evaluation.py
test/test_imputer.py
test/test_imputer_iterators.py
test/test_simple_imputer.py
test/test_utils.py
datawig-0.1.10.dist-info/LICENSE
datawig-0.1.10.dist-info/METADATA
datawig-0.1.10.dist-info/NOTICE
datawig-0.1.10.dist-info/WHEEL
datawig-0.1.10.dist-info/top_level.txt
datawig-0.1.10.dist-info/RECORD
