Metadata-Version: 2.1
Name: datawig
Version: 0.1.10
Summary: Imputation for tables with missing values
Home-page: https://github.com/awslabs/datawig
Author: datawig-dev
Author-email: datawig-dev@amazon.com
Maintainer-email: datawig-dev@amazon.com
License: Apache License 2.0
Platform: UNKNOWN
Classifier: License :: OSI Approved :: Apache Software License
Classifier: Programming Language :: Python :: 3 :: Only
Requires-Python: >=3
Requires-Dist: numpy (>=1.15.0)
Requires-Dist: scikit-learn[alldeps] (>=0.20.0)
Requires-Dist: typing (>=3.6.6)
Requires-Dist: pandas (>=0.22.0)
Requires-Dist: mxnet (>=1.3.0)
